fastask/__init__.py
fastask/ask.py
fastask/config.py
fastask/history.py
fastask/llm.py
fastask-0.4.7.dist-info/LICENSE
fastask-0.4.7.dist-info/METADATA
fastask-0.4.7.dist-info/WHEEL
fastask-0.4.7.dist-info/entry_points.txt
fastask-0.4.7.dist-info/top_level.txt
fastask-0.4.7.dist-info/RECORD
