Metadata-Version: 2.1
Name: fastask
Version: 0.4.7
Summary: The fastest way to get answers in the command line
Author-email: Brian Machado <nah@gmail.com>
License-File: LICENSE
Requires-Dist: requests
Requires-Dist: openai
Requires-Dist: python-dotenv
Requires-Dist: pyyaml
